LICENSE
MANIFEST.in
README.md
README.rst
setup.cfg
setup.py
binconvert/__init__.py
binconvert/convert.py
binconvert/utils.py
binconvert.egg-info/PKG-INFO
binconvert.egg-info/SOURCES.txt
binconvert.egg-info/dependency_links.txt
binconvert.egg-info/entry_points.txt
binconvert.egg-info/not-zip-safe
binconvert.egg-info/requires.txt
binconvert.egg-info/top_level.txt
binconvert/cli/__init__.py
binconvert/cli/script.py
binconvert/tests/__init__.py
binconvert/tests/test_convert.py